gdstdatatable/__init__.py
gdstdatatable/example.py
gdstdatatable/frontend/.prettierrc
gdstdatatable/frontend/build/asset-manifest.json
gdstdatatable/frontend/build/bootstrap.min.css
gdstdatatable/frontend/build/index.html
gdstdatatable/frontend/build/static/css/main.86473e16.css
gdstdatatable/frontend/build/static/css/main.86473e16.css.map
gdstdatatable/frontend/build/static/js/289.cc2e6094.chunk.js
gdstdatatable/frontend/build/static/js/289.cc2e6094.chunk.js.map
gdstdatatable/frontend/build/static/js/509.aa410d29.chunk.js
gdstdatatable/frontend/build/static/js/509.aa410d29.chunk.js.LICENSE.txt
gdstdatatable/frontend/build/static/js/509.aa410d29.chunk.js.map
gdstdatatable/frontend/build/static/js/main.f38b1840.js
gdstdatatable/frontend/build/static/js/main.f38b1840.js.LICENSE.txt
gdstdatatable/frontend/build/static/js/main.f38b1840.js.map
gdstdatatable/frontend/package-lock.json
gdstdatatable/frontend/package.json
gdstdatatable/frontend/public/bootstrap.min.css
gdstdatatable/frontend/public/index.html
gdstdatatable/frontend/src/DatapointTable.tsx
gdstdatatable/frontend/src/index.tsx
gdstdatatable/frontend/src/react-app-env.d.ts
gdstdatatable/frontend/tsconfig.json
gd_st_custom_datatable-0.2.9.dist-info/LICENSE
gd_st_custom_datatable-0.2.9.dist-info/METADATA
gd_st_custom_datatable-0.2.9.dist-info/WHEEL
gd_st_custom_datatable-0.2.9.dist-info/RECORD
