Metadata-Version: 2.1
Name: gd-st-custom-datatable
Version: 0.2.9
Summary: 
Author: Gnomon Digital
Author-email: contact@gnomondigital.com
Requires-Python: >=3.10,<4.0
Classifier: Programming Language :: Python :: 3
Classifier: Programming Language :: Python :: 3.10
Classifier: Programming Language :: Python :: 3.11
Classifier: Programming Language :: Python :: 3.12
Classifier: Programming Language :: Python :: 3.13
Requires-Dist: streamlit (>=1.40.1,<2.0.0)
